Metadata-Version: 2.4
Name: xlizard
Version: 1.1.6
Summary: Extended Lizard with additional static code analysis features
Author: Xor1no
License: MIT
Requires-Dist: jinja2>=3.1.3
Requires-Dist: tqdm>=4.67.1
Requires-Dist: pathspec>=0.12.1
Requires-Dist: lxml>=5.1.0
Requires-Dist: pygments>=2.19.2
Requires-Dist: chardet>=5.2.0
Requires-Dist: psutil>=5.9.8
Requires-Dist: multiprocess>=0.70.16
Requires-Dist: colorama>=0.4.6
